boolean_expression/__init__.py
boolean_expression/py.typed
boolean_expression-0.2.0.post1.dist-info/LICENSE
boolean_expression-0.2.0.post1.dist-info/METADATA
boolean_expression-0.2.0.post1.dist-info/WHEEL
boolean_expression-0.2.0.post1.dist-info/RECORD
