Metadata-Version: 2.1
Name: boolean-expression
Version: 0.2.0.post1
Summary: A simple library for constructing nested boolean expressions and rendering them in various dialects.
License: MIT
Author: Alex Levy
Author-email: mesozoic@users.noreply.github.com
Requires-Python: >=3.8,<4.0
Classifier: License :: OSI Approved :: MIT License
Classifier: Programming Language :: Python :: 3
Classifier: Programming Language :: Python :: 3.8
Classifier: Programming Language :: Python :: 3.9
Classifier: Programming Language :: Python :: 3.10
Classifier: Programming Language :: Python :: 3.11
